mmcv/__init__.py
mmcv/_ext.cp36-win_amd64.pyd
mmcv/opencv_info.py
mmcv/version.py
mmcv/arraymisc/__init__.py
mmcv/arraymisc/quantization.py
mmcv/cnn/__init__.py
mmcv/cnn/alexnet.py
mmcv/cnn/resnet.py
mmcv/cnn/vgg.py
mmcv/cnn/weight_init.py
mmcv/fileio/__init__.py
mmcv/fileio/io.py
mmcv/fileio/parse.py
mmcv/fileio/handlers/__init__.py
mmcv/fileio/handlers/base.py
mmcv/fileio/handlers/json_handler.py
mmcv/fileio/handlers/pickle_handler.py
mmcv/fileio/handlers/yaml_handler.py
mmcv/image/__init__.py
mmcv/image/io.py
mmcv/image/transforms/__init__.py
mmcv/image/transforms/colorspace.py
mmcv/image/transforms/geometry.py
mmcv/image/transforms/normalize.py
mmcv/image/transforms/resize.py
mmcv/parallel/__init__.py
mmcv/parallel/_functions.py
mmcv/parallel/collate.py
mmcv/parallel/data_container.py
mmcv/parallel/data_parallel.py
mmcv/parallel/distributed.py
mmcv/parallel/scatter_gather.py
mmcv/runner/__init__.py
mmcv/runner/checkpoint.py
mmcv/runner/log_buffer.py
mmcv/runner/parallel_test.py
mmcv/runner/priority.py
mmcv/runner/runner.py
mmcv/runner/utils.py
mmcv/runner/hooks/__init__.py
mmcv/runner/hooks/checkpoint.py
mmcv/runner/hooks/closure.py
mmcv/runner/hooks/hook.py
mmcv/runner/hooks/iter_timer.py
mmcv/runner/hooks/lr_updater.py
mmcv/runner/hooks/memory.py
mmcv/runner/hooks/optimizer.py
mmcv/runner/hooks/sampler_seed.py
mmcv/runner/hooks/logger/__init__.py
mmcv/runner/hooks/logger/base.py
mmcv/runner/hooks/logger/pavi.py
mmcv/runner/hooks/logger/tensorboard.py
mmcv/runner/hooks/logger/text.py
mmcv/utils/__init__.py
mmcv/utils/config.py
mmcv/utils/misc.py
mmcv/utils/path.py
mmcv/utils/progressbar.py
mmcv/utils/timer.py
mmcv/video/__init__.py
mmcv/video/io.py
mmcv/video/optflow.py
mmcv/video/processing.py
mmcv/video/optflow_warp/__init__.py
mmcv/visualization/__init__.py
mmcv/visualization/color.py
mmcv/visualization/image.py
mmcv/visualization/optflow.py
mmcv_win-0.2.10.dist-info/LICENSE
mmcv_win-0.2.10.dist-info/METADATA
mmcv_win-0.2.10.dist-info/WHEEL
mmcv_win-0.2.10.dist-info/top_level.txt
mmcv_win-0.2.10.dist-info/RECORD
