Metadata-Version: 2.1
Name: mmcv-win
Version: 0.2.10
Summary: Open MMLab Computer Vision Foundation
Home-page: https://github.com/wswday/mmcv
Author: wswday
Author-email: UNKNOWN
License: UNKNOWN
Keywords: computer vision
Platform: UNKNOWN
Classifier: Development Status :: 4 - Beta
Classifier: License :: OSI Approved :: Apache Software License
Classifier: Operating System :: OS Independent
Classifier: Programming Language :: Python :: 2
Classifier: Programming Language :: Python :: 2.7
Classifier: Programming Language :: Python :: 3
Classifier: Programming Language :: Python :: 3.4
Classifier: Programming Language :: Python :: 3.5
Classifier: Programming Language :: Python :: 3.6
Classifier: Programming Language :: Python :: 3.7
Classifier: Topic :: Utilities
Requires-Dist: numpy (>=1.11.1)
Requires-Dist: pyyaml
Requires-Dist: six
Requires-Dist: addict
Requires-Dist: requests
Requires-Dist: opencv-python
Requires-Dist: Cython
